[
  [
    {
      "PLAYER_ID": 203944,
      "PLAYER_NAME_LAST_FIRST": "Randle, Julius",
      "SORT_ORDER": 1,
      "GP": 81,
      "G": 81,
      "SHOT_TYPE": "Overall",
      "FGA_FREQUENCY": 1,
      "FGM": 6.14,
      "FGA": 9.73,
      "FG_PCT": 0.631,
      "EFG_PCT": 0.637,
      "FG2A_FREQUENCY": 0.943,
      "FG2M": 6.01,
      "FG2A": 9.17,
      "FG2_PCT": 0.655,
      "FG3A_FREQUENCY": 0.057,
      "FG3M": 0.12,
      "FG3A": 0.56,
      "FG3_PCT": 0.222
    }
  ],
  [
    {
      "PLAYER_ID": 203944,
      "PLAYER_NAME_LAST_FIRST": "Randle, Julius",
      "SORT_ORDER": 1,
      "GP": 81,
      "G": 41,
      "SHOT_TYPE": "Catch and Shoot",
      "FGA_FREQUENCY": 0.08,
      "FGM": 0.23,
      "FGA": 0.78,
      "FG_PCT": 0.302,
      "EFG_PCT": 0.381,
      "FG2A_FREQUENCY": 0.036,
      "FG2M": 0.11,
      "FG2A": 0.35,
      "FG2_PCT": 0.321,
      "FG3A_FREQUENCY": 0.044,
      "FG3M": 0.12,
      "FG3A": 0.43,
      "FG3_PCT": 0.286
    },
    {
      "PLAYER_ID": 203944,
      "PLAYER_NAME_LAST_FIRST": "Randle, Julius",
      "SORT_ORDER": 2,
      "GP": 81,
      "G": 36,
      "SHOT_TYPE": "Pull Ups",
      "FGA_FREQUENCY": 0.06,
      "FGM": 0.17,
      "FGA": 0.58,
      "FG_PCT": 0.298,
      "EFG_PCT": 0.298,
      "FG2A_FREQUENCY": 0.048,
      "FG2M": 0.17,
      "FG2A": 0.47,
      "FG2_PCT": 0.368,
      "FG3A_FREQUENCY": 0.011,
      "FG3M": 0,
      "FG3A": 0.11,
      "FG3_PCT": 0
    },
    {
      "PLAYER_ID": 203944,
      "PLAYER_NAME_LAST_FIRST": "Randle, Julius",
      "SORT_ORDER": 3,
      "GP": 81,
      "G": 81,
      "SHOT_TYPE": "Less than 10 ft",
      "FGA_FREQUENCY": 0.853,
      "FGM": 5.7,
      "FGA": 8.3,
      "FG_PCT": 0.688,
      "EFG_PCT": 0.688,
      "FG2A_FREQUENCY": 0.853,
      "FG2M": 5.7,
      "FG2A": 8.3,
      "FG2_PCT": 0.688,
      "FG3A_FREQUENCY": 0,
      "FG3M": 0,
      "FG3A": 0,
      "FG3_PCT": null
    },
    {
      "PLAYER_ID": 203944,
      "PLAYER_NAME_LAST_FIRST": "Randle, Julius",
      "SORT_ORDER": 4,
      "GP": 81,
      "G": 6,
      "SHOT_TYPE": "Other",
      "FGA_FREQUENCY": 0.008,
      "FGM": 0.02,
      "FGA": 0.07,
      "FG_PCT": 0.333,
      "EFG_PCT": 0.333,
      "FG2A_FREQUENCY": 0.006,
      "FG2M": 0.02,
      "FG2A": 0.06,
      "FG2_PCT": 0.4,
      "FG3A_FREQUENCY": 0.001,
      "FG3M": 0,
      "FG3A": 0.01,
      "FG3_PCT": 0
    }
  ],
  [
    {
      "PLAYER_ID": 203944,
      "PLAYER_NAME_LAST_FIRST": "Randle, Julius",
      "SORT_ORDER": 1,
      "GP": 81,
      "G": 41,
      "SHOT_CLOCK_RANGE": "24-22",
      "FGA_FREQUENCY": 0.072,
      "FGM": 0.53,
      "FGA": 0.7,
      "FG_PCT": 0.754,
      "EFG_PCT": 0.754,
      "FG2A_FREQUENCY": 0.072,
      "FG2M": 0.53,
      "FG2A": 0.7,
      "FG2_PCT": 0.754,
      "FG3A_FREQUENCY": 0,
      "FG3M": 0,
      "FG3A": 0,
      "FG3_PCT": null
    },
    {
      "PLAYER_ID": 203944,
      "PLAYER_NAME_LAST_FIRST": "Randle, Julius",
      "SORT_ORDER": 2,
      "GP": 81,
      "G": 68,
      "SHOT_CLOCK_RANGE": "22-18 Very Early",
      "FGA_FREQUENCY": 0.189,
      "FGM": 1.32,
      "FGA": 1.84,
      "FG_PCT": 0.718,
      "EFG_PCT": 0.718,
      "FG2A_FREQUENCY": 0.187,
      "FG2M": 1.32,
      "FG2A": 1.81,
      "FG2_PCT": 0.728,
      "FG3A_FREQUENCY": 0.003,
      "FG3M": 0,
      "FG3A": 0.02,
      "FG3_PCT": 0
    },
    {
      "PLAYER_ID": 203944,
      "PLAYER_NAME_LAST_FIRST": "Randle, Julius",
      "SORT_ORDER": 3,
      "GP": 81,
      "G": 67,
      "SHOT_CLOCK_RANGE": "18-15 Early",
      "FGA_FREQUENCY": 0.179,
      "FGM": 1.12,
      "FGA": 1.74,
      "FG_PCT": 0.645,
      "EFG_PCT": 0.656,
      "FG2A_FREQUENCY": 0.174,
      "FG2M": 1.09,
      "FG2A": 1.69,
      "FG2_PCT": 0.642,
      "FG3A_FREQUENCY": 0.005,
      "FG3M": 0.04,
      "FG3A": 0.05,
      "FG3_PCT": 0.75
    },
    {
      "PLAYER_ID": 203944,
      "PLAYER_NAME_LAST_FIRST": "Randle, Julius",
      "SORT_ORDER": 4,
      "GP": 81,
      "G": 78,
      "SHOT_CLOCK_RANGE": "15-7 Average",
      "FGA_FREQUENCY": 0.395,
      "FGM": 2.23,
      "FGA": 3.84,
      "FG_PCT": 0.582,
      "EFG_PCT": 0.587,
      "FG2A_FREQUENCY": 0.369,
      "FG2M": 2.2,
      "FG2A": 3.59,
      "FG2_PCT": 0.612,
      "FG3A_FREQUENCY": 0.025,
      "FG3M": 0.04,
      "FG3A": 0.25,
      "FG3_PCT": 0.15
    },
    {
      "PLAYER_ID": 203944,
      "PLAYER_NAME_LAST_FIRST": "Randle, Julius",
      "SORT_ORDER": 5,
      "GP": 81,
      "G": 46,
      "SHOT_CLOCK_RANGE": "7-4 Late",
      "FGA_FREQUENCY": 0.091,
      "FGM": 0.62,
      "FGA": 0.89,
      "FG_PCT": 0.694,
      "EFG_PCT": 0.708,
      "FG2A_FREQUENCY": 0.086,
      "FG2M": 0.59,
      "FG2A": 0.84,
      "FG2_PCT": 0.706,
      "FG3A_FREQUENCY": 0.005,
      "FG3M": 0.02,
      "FG3A": 0.05,
      "FG3_PCT": 0.5
    },
    {
      "PLAYER_ID": 203944,
      "PLAYER_NAME_LAST_FIRST": "Randle, Julius",
      "SORT_ORDER": 6,
      "GP": 81,
      "G": 37,
      "SHOT_CLOCK_RANGE": "4-0 Very Late",
      "FGA_FREQUENCY": 0.074,
      "FGM": 0.31,
      "FGA": 0.72,
      "FG_PCT": 0.431,
      "EFG_PCT": 0.448,
      "FG2A_FREQUENCY": 0.055,
      "FG2M": 0.28,
      "FG2A": 0.53,
      "FG2_PCT": 0.535,
      "FG3A_FREQUENCY": 0.019,
      "FG3M": 0.02,
      "FG3A": 0.19,
      "FG3_PCT": 0.133
    }
  ],
  [
    {
      "PLAYER_ID": 203944,
      "PLAYER_NAME_LAST_FIRST": "Randle, Julius",
      "SORT_ORDER": 1,
      "GP": 81,
      "G": 78,
      "DRIBBLE_RANGE": "0 Dribbles",
      "FGA_FREQUENCY": 0.353,
      "FGM": 2.37,
      "FGA": 3.43,
      "FG_PCT": 0.691,
      "EFG_PCT": 0.709,
      "FG2A_FREQUENCY": 0.307,
      "FG2M": 2.25,
      "FG2A": 2.99,
      "FG2_PCT": 0.752,
      "FG3A_FREQUENCY": 0.046,
      "FG3M": 0.12,
      "FG3A": 0.44,
      "FG3_PCT": 0.278
    },
    {
      "PLAYER_ID": 203944,
      "PLAYER_NAME_LAST_FIRST": "Randle, Julius",
      "SORT_ORDER": 2,
      "GP": 81,
      "G": 70,
      "DRIBBLE_RANGE": "1 Dribble",
      "FGA_FREQUENCY": 0.235,
      "FGM": 1.38,
      "FGA": 2.28,
      "FG_PCT": 0.605,
      "EFG_PCT": 0.605,
      "FG2A_FREQUENCY": 0.23,
      "FG2M": 1.38,
      "FG2A": 2.23,
      "FG2_PCT": 0.619,
      "FG3A_FREQUENCY": 0.005,
      "FG3M": 0,
      "FG3A": 0.05,
      "FG3_PCT": 0
    },
    {
      "PLAYER_ID": 203944,
      "PLAYER_NAME_LAST_FIRST": "Randle, Julius",
      "SORT_ORDER": 3,
      "GP": 81,
      "G": 53,
      "DRIBBLE_RANGE": "2 Dribbles",
      "FGA_FREQUENCY": 0.148,
      "FGM": 0.81,
      "FGA": 1.44,
      "FG_PCT": 0.564,
      "EFG_PCT": 0.564,
      "FG2A_FREQUENCY": 0.146,
      "FG2M": 0.81,
      "FG2A": 1.42,
      "FG2_PCT": 0.574,
      "FG3A_FREQUENCY": 0.003,
      "FG3M": 0,
      "FG3A": 0.02,
      "FG3_PCT": 0
    },
    {
      "PLAYER_ID": 203944,
      "PLAYER_NAME_LAST_FIRST": "Randle, Julius",
      "SORT_ORDER": 4,
      "GP": 81,
      "G": 71,
      "DRIBBLE_RANGE": "3-6 Dribbles",
      "FGA_FREQUENCY": 0.222,
      "FGM": 1.32,
      "FGA": 2.16,
      "FG_PCT": 0.611,
      "EFG_PCT": 0.611,
      "FG2A_FREQUENCY": 0.22,
      "FG2M": 1.32,
      "FG2A": 2.14,
      "FG2_PCT": 0.618,
      "FG3A_FREQUENCY": 0.003,
      "FG3M": 0,
      "FG3A": 0.02,
      "FG3_PCT": 0
    },
    {
      "PLAYER_ID": 203944,
      "PLAYER_NAME_LAST_FIRST": "Randle, Julius",
      "SORT_ORDER": 5,
      "GP": 81,
      "G": 28,
      "DRIBBLE_RANGE": "7+ Dribbles",
      "FGA_FREQUENCY": 0.042,
      "FGM": 0.25,
      "FGA": 0.41,
      "FG_PCT": 0.606,
      "EFG_PCT": 0.606,
      "FG2A_FREQUENCY": 0.041,
      "FG2M": 0.25,
      "FG2A": 0.4,
      "FG2_PCT": 0.625,
      "FG3A_FREQUENCY": 0.001,
      "FG3M": 0,
      "FG3A": 0.01,
      "FG3_PCT": 0
    }
  ],
  [
    {
      "PLAYER_ID": 203944,
      "PLAYER_NAME_LAST_FIRST": "Randle, Julius",
      "SORT_ORDER": 1,
      "GP": 81,
      "G": 74,
      "CLOSE_DEF_DIST_RANGE": "0-2 Feet - Very Tight",
      "FGA_FREQUENCY": 0.251,
      "FGM": 1.68,
      "FGA": 2.44,
      "FG_PCT": 0.687,
      "EFG_PCT": 0.687,
      "FG2A_FREQUENCY": 0.251,
      "FG2M": 1.68,
      "FG2A": 2.44,
      "FG2_PCT": 0.687,
      "FG3A_FREQUENCY": 0,
      "FG3M": 0,
      "FG3A": 0,
      "FG3_PCT": null
    },
    {
      "PLAYER_ID": 203944,
      "PLAYER_NAME_LAST_FIRST": "Randle, Julius",
      "SORT_ORDER": 2,
      "GP": 81,
      "G": 79,
      "CLOSE_DEF_DIST_RANGE": "2-4 Feet - Tight",
      "FGA_FREQUENCY": 0.532,
      "FGM": 3.42,
      "FGA": 5.17,
      "FG_PCT": 0.661,
      "EFG_PCT": 0.662,
      "FG2A_FREQUENCY": 0.528,
      "FG2M": 3.41,
      "FG2A": 5.14,
      "FG2_PCT": 0.663,
      "FG3A_FREQUENCY": 0.004,
      "FG3M": 0.01,
      "FG3A": 0.04,
      "FG3_PCT": 0.333
    },
    {
      "PLAYER_ID": 203944,
      "PLAYER_NAME_LAST_FIRST": "Randle, Julius",
      "SORT_ORDER": 3,
      "GP": 81,
      "G": 58,
      "CLOSE_DEF_DIST_RANGE": "4-6 Feet - Open",
      "FGA_FREQUENCY": 0.119,
      "FGM": 0.67,
      "FGA": 1.16,
      "FG_PCT": 0.574,
      "EFG_PCT": 0.585,
      "FG2A_FREQUENCY": 0.107,
      "FG2M": 0.64,
      "FG2A": 1.04,
      "FG2_PCT": 0.619,
      "FG3A_FREQUENCY": 0.013,
      "FG3M": 0.02,
      "FG3A": 0.12,
      "FG3_PCT": 0.2
    },
    {
      "PLAYER_ID": 203944,
      "PLAYER_NAME_LAST_FIRST": "Randle, Julius",
      "SORT_ORDER": 4,
      "GP": 81,
      "G": 50,
      "CLOSE_DEF_DIST_RANGE": "6+ Feet - Wide Open",
      "FGA_FREQUENCY": 0.098,
      "FGM": 0.37,
      "FGA": 0.95,
      "FG_PCT": 0.39,
      "EFG_PCT": 0.435,
      "FG2A_FREQUENCY": 0.057,
      "FG2M": 0.28,
      "FG2A": 0.56,
      "FG2_PCT": 0.511,
      "FG3A_FREQUENCY": 0.041,
      "FG3M": 0.09,
      "FG3A": 0.4,
      "FG3_PCT": 0.219
    }
  ],
  [
    {
      "PLAYER_ID": 203944,
      "PLAYER_NAME_LAST_FIRST": "Randle, Julius",
      "SORT_ORDER": 1,
      "GP": 81,
      "G": 2,
      "CLOSE_DEF_DIST_RANGE": "0-2 Feet - Very Tight",
      "FGA_FREQUENCY": 0.003,
      "FGM": 0.02,
      "FGA": 0.02,
      "FG_PCT": 1,
      "EFG_PCT": 1,
      "FG2A_FREQUENCY": 0.003,
      "FG2M": 0.02,
      "FG2A": 0.02,
      "FG2_PCT": 1,
      "FG3A_FREQUENCY": 0,
      "FG3M": 0,
      "FG3A": 0,
      "FG3_PCT": null
    },
    {
      "PLAYER_ID": 203944,
      "PLAYER_NAME_LAST_FIRST": "Randle, Julius",
      "SORT_ORDER": 2,
      "GP": 81,
      "G": 14,
      "CLOSE_DEF_DIST_RANGE": "2-4 Feet - Tight",
      "FGA_FREQUENCY": 0.02,
      "FGM": 0.09,
      "FGA": 0.2,
      "FG_PCT": 0.438,
      "EFG_PCT": 0.469,
      "FG2A_FREQUENCY": 0.016,
      "FG2M": 0.07,
      "FG2A": 0.16,
      "FG2_PCT": 0.462,
      "FG3A_FREQUENCY": 0.004,
      "FG3M": 0.01,
      "FG3A": 0.04,
      "FG3_PCT": 0.333
    },
    {
      "PLAYER_ID": 203944,
      "PLAYER_NAME_LAST_FIRST": "Randle, Julius",
      "SORT_ORDER": 3,
      "GP": 81,
      "G": 31,
      "CLOSE_DEF_DIST_RANGE": "4-6 Feet - Open",
      "FGA_FREQUENCY": 0.043,
      "FGM": 0.11,
      "FGA": 0.42,
      "FG_PCT": 0.265,
      "EFG_PCT": 0.294,
      "FG2A_FREQUENCY": 0.03,
      "FG2M": 0.09,
      "FG2A": 0.3,
      "FG2_PCT": 0.292,
      "FG3A_FREQUENCY": 0.013,
      "FG3M": 0.02,
      "FG3A": 0.12,
      "FG3_PCT": 0.2
    },
    {
      "PLAYER_ID": 203944,
      "PLAYER_NAME_LAST_FIRST": "Randle, Julius",
      "SORT_ORDER": 4,
      "GP": 81,
      "G": 46,
      "CLOSE_DEF_DIST_RANGE": "6+ Feet - Wide Open",
      "FGA_FREQUENCY": 0.081,
      "FGM": 0.21,
      "FGA": 0.79,
      "FG_PCT": 0.266,
      "EFG_PCT": 0.32,
      "FG2A_FREQUENCY": 0.041,
      "FG2M": 0.12,
      "FG2A": 0.4,
      "FG2_PCT": 0.313,
      "FG3A_FREQUENCY": 0.041,
      "FG3M": 0.09,
      "FG3A": 0.4,
      "FG3_PCT": 0.219
    }
  ],
  [
    {
      "PLAYER_ID": 203944,
      "PLAYER_NAME_LAST_FIRST": "Randle, Julius",
      "SORT_ORDER": 1,
      "GP": 81,
      "G": 78,
      "TOUCH_TIME_RANGE": "Touch < 2 Seconds",
      "FGA_FREQUENCY": 0.449,
      "FGM": 3.09,
      "FGA": 4.37,
      "FG_PCT": 0.706,
      "EFG_PCT": 0.72,
      "FG2A_FREQUENCY": 0.404,
      "FG2M": 2.96,
      "FG2A": 3.93,
      "FG2_PCT": 0.755,
      "FG3A_FREQUENCY": 0.046,
      "FG3M": 0.12,
      "FG3A": 0.44,
      "FG3_PCT": 0.278
    },
    {
      "PLAYER_ID": 203944,
      "PLAYER_NAME_LAST_FIRST": "Randle, Julius",
      "SORT_ORDER": 2,
      "GP": 81,
      "G": 79,
      "TOUCH_TIME_RANGE": "Touch 2-6 Seconds",
      "FGA_FREQUENCY": 0.448,
      "FGM": 2.44,
      "FGA": 4.36,
      "FG_PCT": 0.561,
      "EFG_PCT": 0.561,
      "FG2A_FREQUENCY": 0.437,
      "FG2M": 2.44,
      "FG2A": 4.25,
      "FG2_PCT": 0.576,
      "FG3A_FREQUENCY": 0.011,
      "FG3M": 0,
      "FG3A": 0.11,
      "FG3_PCT": 0
    },
    {
      "PLAYER_ID": 203944,
      "PLAYER_NAME_LAST_FIRST": "Randle, Julius",
      "SORT_ORDER": 3,
      "GP": 81,
      "G": 51,
      "TOUCH_TIME_RANGE": "Touch 6+ Seconds",
      "FGA_FREQUENCY": 0.103,
      "FGM": 0.6,
      "FGA": 1,
      "FG_PCT": 0.605,
      "EFG_PCT": 0.605,
      "FG2A_FREQUENCY": 0.103,
      "FG2M": 0.6,
      "FG2A": 1,
      "FG2_PCT": 0.605,
      "FG3A_FREQUENCY": 0,
      "FG3M": 0,
      "FG3A": 0,
      "FG3_PCT": null
    }
  ]
]